{
    "bug_id": 44,
    "bug_type": "SF",
    "buggy_lines": "",
    "code": "  void add(String newcode) {\n    maybeEndStatement();\n\n    if (newcode.length() == 0) {\n      return;\n    }\n\n    char c = newcode.charAt(0);\n    if ((isWordChar(c) || c == '\\\\') &&\n        isWordChar(getLastChar())) {\n      // need space to separate. This is not pretty printing.\n      // For example: \"return foo;\"\n      append(\" \");\n      // Do not allow a forward slash to appear after a DIV.\n      // For example,\n      // REGEXP DIV REGEXP\n      // is valid and should print like\n      // / // / /\n    }\n\n    append(newcode);\n  }",
    "fixed_code": "  void add(String newcode) {\n    maybeEndStatement();\n\n    if (newcode.length() == 0) {\n      return;\n    }\n\n    char c = newcode.charAt(0);\n    if ((isWordChar(c) || c == '\\\\') &&\n        isWordChar(getLastChar())) {\n      // need space to separate. This is not pretty printing.\n      // For example: \"return foo;\"\n      append(\" \");\n    } else if (c == '/' && getLastChar() == '/') {\n      // Do not allow a forward slash to appear after a DIV.\n      // For example,\n      // REGEXP DIV REGEXP\n      // is valid and should print like\n      // / // / /\n      append(\" \");\n    }\n\n    append(newcode);\n  }",
    "fixed_lines": "    } else if (c == '/' && getLastChar() == '/') {\n      append(\" \");",
    "masked_code": "  void add(String newcode) {\n    maybeEndStatement();\n\n    if (newcode.length() == 0) {\n      return;\n    }\n\n    char c = newcode.charAt(0);\n    if ((isWordChar(c) || c == '\\\\') &&\n        isWordChar(getLastChar())) {\n      // need space to separate. This is not pretty printing.\n      // For example: \"return foo;\"\n      append(\" \");\n      // Do not allow a forward slash to appear after a DIV.\n      // For example,\n      // REGEXP DIV REGEXP\n      // is valid and should print like\n      // / // / /\n>>> [ INFILL ] <<<\n    }\n\n    append(newcode);\n  }",
    "project": "Closure",
    "test_error_message": "junit.framework.ComparisonFailure: expected:<alert(/ //[ ]/ /)> but was:<alert(/ //[]/ /)>",
    "test_framework": "defects4j",
    "test_line": "    assertEquals(expected,",
    "test_name": "testIssue620",
    "test_suite": "com.google.javascript.jscomp.CodePrinterTest"
}