{
    "bug_id": 102,
    "bug_type": "SF",
    "buggy_lines": "",
    "code": "    public double chiSquare(double[] expected, long[] observed)\n        throws IllegalArgumentException {\n        if ((expected.length < 2) || (expected.length != observed.length)) {\n            throw new IllegalArgumentException(\n                    \"observed, expected array lengths incorrect\");\n        }\n        if (!isPositive(expected) || !isNonNegative(observed)) {\n            throw new IllegalArgumentException(\n                \"observed counts must be non-negative and expected counts must be postive\");\n        }\n        double sumSq = 0.0d;\n        double dev = 0.0d;\n        for (int i = 0; i < observed.length; i++) {\n                dev = ((double) observed[i] - expected[i]);\n                sumSq += dev * dev / expected[i];\n        }\n        return sumSq;\n    }",
    "fixed_code": "    public double chiSquare(double[] expected, long[] observed)\n        throws IllegalArgumentException {\n        if ((expected.length < 2) || (expected.length != observed.length)) {\n            throw new IllegalArgumentException(\n                    \"observed, expected array lengths incorrect\");\n        }\n        if (!isPositive(expected) || !isNonNegative(observed)) {\n            throw new IllegalArgumentException(\n                \"observed counts must be non-negative and expected counts must be postive\");\n        }\n        double sumExpected = 0d;\n        double sumObserved = 0d;\n        for (int i = 0; i < observed.length; i++) {\n            sumExpected += expected[i];\n            sumObserved += observed[i];\n        }\n        double ratio = 1.0d;\n        boolean rescale = false;\n        if (Math.abs(sumExpected - sumObserved) > 10E-6) {\n            ratio = sumObserved / sumExpected;\n            rescale = true;\n        }\n        double sumSq = 0.0d;\n        double dev = 0.0d;\n        for (int i = 0; i < observed.length; i++) {\n            if (rescale) {\n                dev = ((double) observed[i] - ratio * expected[i]);\n                sumSq += dev * dev / (ratio * expected[i]);\n            } else {\n                dev = ((double) observed[i] - expected[i]);\n                sumSq += dev * dev / expected[i];\n            }\n        }\n        return sumSq;\n    }",
    "fixed_lines": "        double sumExpected = 0d;\n        double sumObserved = 0d;\n        for (int i = 0; i < observed.length; i++) {\n            sumExpected += expected[i];\n            sumObserved += observed[i];\n        }\n        double ratio = 1.0d;\n        boolean rescale = false;\n        if (Math.abs(sumExpected - sumObserved) > 10E-6) {\n            ratio = sumObserved / sumExpected;\n            rescale = true;\n        }\n            if (rescale) {\n                dev = ((double) observed[i] - ratio * expected[i]);\n                sumSq += dev * dev / (ratio * expected[i]);\n            } else {\n            }",
    "masked_code": "    public double chiSquare(double[] expected, long[] observed)\n        throws IllegalArgumentException {\n        if ((expected.length < 2) || (expected.length != observed.length)) {\n            throw new IllegalArgumentException(\n                    \"observed, expected array lengths incorrect\");\n        }\n        if (!isPositive(expected) || !isNonNegative(observed)) {\n            throw new IllegalArgumentException(\n                \"observed counts must be non-negative and expected counts must be postive\");\n        }\n        double sumSq = 0.0d;\n        double dev = 0.0d;\n        for (int i = 0; i < observed.length; i++) {\n                dev = ((double) observed[i] - expected[i]);\n                sumSq += dev * dev / expected[i];\n>>> [ INFILL ] <<<\n        }\n        return sumSq;\n    }",
    "project": "Math",
    "test_error_message": "junit.framework.AssertionFailedError: chi-square test statistic expected:<114875.90421929007> but was:<3624883.3429077636>",
    "test_framework": "defects4j",
    "test_line": "",
    "test_name": "testChiSquareLargeTestStatistic",
    "test_suite": "org.apache.commons.math.stat.inference.ChiSquareFactoryTest"
}